{"evidence_id":"QRT-P2.3-R1-2026-07-03","unit_id":"P2.3","stacked_base_sha":"6c99531510279972da457962f56baa07518b47fe","state":"LOCAL_PASS_CI_PENDING","implementation":"src/quantum/pilot/runtime_persistence_bridge.py","tests":{"module":"tests/test_runtime_persistence_bridge.py","bridge":28,"combined":88,"failures":0,"errors":0,"resource_warnings":0,"compilation":"PASS"},"verified_properties":["ATOMIC_RUNTIME_CAPTURE","SECONDARY_INDEX_ATTESTATION","EXTERNAL_RECEIPT_ATTESTATION_REQUIRED","ROLLBACK_GUARD","TENANT_SET_BINDING","DETACHED_RESTORE_ONLY","TENANT_ACCOUNT_MEMBERSHIP_QUARANTINE","SESSION_REVOCATION","ISSUED_INVITE_REVOCATION","TERMINAL_INVITE_EXCLUSION","EXACT_TYPE_BOUNDARY","PLAINTEXT_BEARER_ABSENT"],"review_independence":"SAME_AUTOMATION_NOT_INDEPENDENT","hard_boundaries":{"real_data":false,"production_credentials":false,"live_runtime_activation":false,"protected_main_merge":false,"deploy":false,"release":false},"next_required":["FOUNDATION_CI_SUCCESS","OSS_ADMISSION_CI_SUCCESS","ZERO_REVIEW_THREADS","INTERNAL_REVIEW_PASS"]}
